Workbook

Sheet Test Cases
A1: SmartEPT — Session Test Case Suite (11–12 Aug 2026)
A2: Covers: progressive lifetime pricing · admin deletes · coupon visibility · dunning fix · branding · product login fix · client-wise SMTP · forgot-password OTP
A4: TC ID | B4: Module | C4: Priority | D4: Test Case | E4: Preconditions | F4: Steps | G4: Expected Result | H4: Status | I4: Tested By | J4: Remarks
A5: TC-001 | B5: Pricing — /buy (Perpetual) | C5: P1 | D5: Perpetual price for 5 monitored users | E5: Bands: 5–15 ₹15k · 16–30 ₹25k · 31–50 ₹40k · 51–100 ₹60k · 101–150 ₹75k · 151–200 ₹90k. Hard refresh /buy, Own·Perpetual, INR. | F5: Set Monitored users = 5; read the licence line in the price panel | G5: Licence price shows exactly ₹15,000 (first-band flat (minimum package)); GST 18% on top; total = licence+setup(if ticked)+GST
A6: TC-002 | B6: Pricing — /buy (Perpetual) | C6: P1 | D6: Perpetual price for 10 monitored users | E6: Bands: 5–15 ₹15k · 16–30 ₹25k · 31–50 ₹40k · 51–100 ₹60k · 101–150 ₹75k · 151–200 ₹90k. Hard refresh /buy, Own·Perpetual, INR. | F6: Set Monitored users = 10; read the licence line in the price panel | G6: Licence price shows exactly ₹15,000 (first-band flat); GST 18% on top; total = licence+setup(if ticked)+GST
A7: TC-003 | B7: Pricing — /buy (Perpetual) | C7: P1 | D7: Perpetual price for 15 monitored users | E7: Bands: 5–15 ₹15k · 16–30 ₹25k · 31–50 ₹40k · 51–100 ₹60k · 101–150 ₹75k · 151–200 ₹90k. Hard refresh /buy, Own·Perpetual, INR. | F7: Set Monitored users = 15; read the licence line in the price panel | G7: Licence price shows exactly ₹15,000 (milestone exact); GST 18% on top; total = licence+setup(if ticked)+GST
A8: TC-004 | B8: Pricing — /buy (Perpetual) | C8: P1 | D8: Perpetual price for 16 monitored users | E8: Bands: 5–15 ₹15k · 16–30 ₹25k · 31–50 ₹40k · 51–100 ₹60k · 101–150 ₹75k · 151–200 ₹90k. Hard refresh /buy, Own·Perpetual, INR. | F8: Set Monitored users = 16; read the licence line in the price panel | G8: Licence price shows exactly ₹15,667 (15,000 + 1×(10,000/15), single final round); GST 18% on top; total = licence+setup(if ticked)+GST
A9: TC-005 | B9: Pricing — /buy (Perpetual) | C9: P1 | D9: Perpetual price for 30 monitored users | E9: Bands: 5–15 ₹15k · 16–30 ₹25k · 31–50 ₹40k · 51–100 ₹60k · 101–150 ₹75k · 151–200 ₹90k. Hard refresh /buy, Own·Perpetual, INR. | F9: Set Monitored users = 30; read the licence line in the price panel | G9: Licence price shows exactly ₹25,000 (milestone exact); GST 18% on top; total = licence+setup(if ticked)+GST
A10: TC-006 | B10: Pricing — /buy (Perpetual) | C10: P1 | D10: Perpetual price for 31 monitored users | E10: Bands: 5–15 ₹15k · 16–30 ₹25k · 31–50 ₹40k · 51–100 ₹60k · 101–150 ₹75k · 151–200 ₹90k. Hard refresh /buy, Own·Perpetual, INR. | F10: Set Monitored users = 31; read the licence line in the price panel | G10: Licence price shows exactly ₹25,750 (25,000 + 1×750); GST 18% on top; total = licence+setup(if ticked)+GST
A11: TC-007 | B11: Pricing — /buy (Perpetual) | C11: P1 | D11: Perpetual price for 41 monitored users | E11: Bands: 5–15 ₹15k · 16–30 ₹25k · 31–50 ₹40k · 51–100 ₹60k · 101–150 ₹75k · 151–200 ₹90k. Hard refresh /buy, Own·Perpetual, INR. | F11: Set Monitored users = 41; read the licence line in the price panel | G11: Licence price shows exactly ₹33,250 (25,000 + 11×750); GST 18% on top; total = licence+setup(if ticked)+GST
A12: TC-008 | B12: Pricing — /buy (Perpetual) | C12: P1 | D12: Perpetual price for 50 monitored users | E12: Bands: 5–15 ₹15k · 16–30 ₹25k · 31–50 ₹40k · 51–100 ₹60k · 101–150 ₹75k · 151–200 ₹90k. Hard refresh /buy, Own·Perpetual, INR. | F12: Set Monitored users = 50; read the licence line in the price panel | G12: Licence price shows exactly ₹40,000 (milestone exact); GST 18% on top; total = licence+setup(if ticked)+GST
A13: TC-009 | B13: Pricing — /buy (Perpetual) | C13: P1 | D13: Perpetual price for 51 monitored users | E13: Bands: 5–15 ₹15k · 16–30 ₹25k · 31–50 ₹40k · 51–100 ₹60k · 101–150 ₹75k · 151–200 ₹90k. Hard refresh /buy, Own·Perpetual, INR. | F13: Set Monitored users = 51; read the licence line in the price panel | G13: Licence price shows exactly ₹40,400 (40,000 + 1×400); GST 18% on top; total = licence+setup(if ticked)+GST
A14: TC-010 | B14: Pricing — /buy (Perpetual) | C14: P1 | D14: Perpetual price for 61 monitored users | E14: Bands: 5–15 ₹15k · 16–30 ₹25k · 31–50 ₹40k · 51–100 ₹60k · 101–150 ₹75k · 151–200 ₹90k. Hard refresh /buy, Own·Perpetual, INR. | F14: Set Monitored users = 61; read the licence line in the price panel | G14: Licence price shows exactly ₹44,400 (40,000 + 11×400); GST 18% on top; total = licence+setup(if ticked)+GST
A15: TC-011 | B15: Pricing — /buy (Perpetual) | C15: P1 | D15: Perpetual price for 100 monitored users | E15: Bands: 5–15 ₹15k · 16–30 ₹25k · 31–50 ₹40k · 51–100 ₹60k · 101–150 ₹75k · 151–200 ₹90k. Hard refresh /buy, Own·Perpetual, INR. | F15: Set Monitored users = 100; read the licence line in the price panel | G15: Licence price shows exactly ₹60,000 (milestone exact); GST 18% on top; total = licence+setup(if ticked)+GST
A16: TC-012 | B16: Pricing — /buy (Perpetual) | C16: P1 | D16: Perpetual price for 101 monitored users | E16: Bands: 5–15 ₹15k · 16–30 ₹25k · 31–50 ₹40k · 51–100 ₹60k · 101–150 ₹75k · 151–200 ₹90k. Hard refresh /buy, Own·Perpetual, INR. | F16: Set Monitored users = 101; read the licence line in the price panel | G16: Licence price shows exactly ₹60,300 (60,000 + 1×300); GST 18% on top; total = licence+setup(if ticked)+GST
... A81: TC-077 | B81: Product — Forgot password (OTP) | C81: P2 | D81: Request throttle | E81: Console login card (smartept.test/admin or /<slug>) | F81: Request codes 6+ times within a minute | G81: 429 after the 5th; resumes next minute

Sheet Summary
A1: SmartEPT Session Test Suite — Execution Summary
A2: Fill ONLY the yellow columns on 'Test Cases': Status (PASS / FAIL / BLOCKED), Tested By (your name, e.g. R. Sharma), Remarks (defect notes / evidence link).
A3: Priorities: P1 = must pass before deploy/sign-off · P2 = should pass. Every P1 FAIL must be reported to Ejaz sir immediately.
A5: Module | B5: Cases | C5: P1 | D5: Executed | E5: Passed | F5: Failed
A6: Pricing — /buy (Perpetual) | B6: =COUNTIF('Test Cases'!$B$5:$B$81,A6) -> 23 | C6: =COUNTIFS('Test Cases'!$B$5:$B$81,A6,'Test Cases'!$C$5:$C$81,"P1") -> 21 | D6: =COUNTIFS('Test Cases'!$B$5:$B$81,A6,'Test Cases'!$H$5:$H$81,"<>") -> 0 | E6: =COUNTIFS('Test Cases'!$B$5:$B$81,A6,'Test Cases'!$H$5:$H$81,"PASS") -> 0 | F6: =COUNTIFS('Test Cases'!$B$5:$B$81,A6,'Test Cases'!$H$5:$H$81,"FAIL") -> 0
A7: Pricing — Trial/Sign-up page | B7: =COUNTIF('Test Cases'!$B$5:$B$81,A7) -> 4 | C7: =COUNTIFS('Test Cases'!$B$5:$B$81,A7,'Test Cases'!$C$5:$C$81,"P1") -> 2 | D7: =COUNTIFS('Test Cases'!$B$5:$B$81,A7,'Test Cases'!$H$5:$H$81,"<>") -> 0 | E7: =COUNTIFS('Test Cases'!$B$5:$B$81,A7,'Test Cases'!$H$5:$H$81,"PASS") -> 0 | F7: =COUNTIFS('Test Cases'!$B$5:$B$81,A7,'Test Cases'!$H$5:$H$81,"FAIL") -> 0
A8: Pricing — Client portal | B8: =COUNTIF('Test Cases'!$B$5:$B$81,A8) -> 3 | C8: =COUNTIFS('Test Cases'!$B$5:$B$81,A8,'Test Cases'!$C$5:$C$81,"P1") -> 2 | D8: =COUNTIFS('Test Cases'!$B$5:$B$81,A8,'Test Cases'!$H$5:$H$81,"<>") -> 0 | E8: =COUNTIFS('Test Cases'!$B$5:$B$81,A8,'Test Cases'!$H$5:$H$81,"PASS") -> 0 | F8: =COUNTIFS('Test Cases'!$B$5:$B$81,A8,'Test Cases'!$H$5:$H$81,"FAIL") -> 0
A9: Pricing — Landing page | B9: =COUNTIF('Test Cases'!$B$5:$B$81,A9) -> 3 | C9: =COUNTIFS('Test Cases'!$B$5:$B$81,A9,'Test Cases'!$C$5:$C$81,"P1") -> 1 | D9: =COUNTIFS('Test Cases'!$B$5:$B$81,A9,'Test Cases'!$H$5:$H$81,"<>") -> 0 | E9: =COUNTIFS('Test Cases'!$B$5:$B$81,A9,'Test Cases'!$H$5:$H$81,"PASS") -> 0 | F9: =COUNTIFS('Test Cases'!$B$5:$B$81,A9,'Test Cases'!$H$5:$H$81,"FAIL") -> 0
A10: Admin — Pricing band editor | B10: =COUNTIF('Test Cases'!$B$5:$B$81,A10) -> 8 | C10: =COUNTIFS('Test Cases'!$B$5:$B$81,A10,'Test Cases'!$C$5:$C$81,"P1") -> 6 | D10: =COUNTIFS('Test Cases'!$B$5:$B$81,A10,'Test Cases'!$H$5:$H$81,"<>") -> 0 | E10: =COUNTIFS('Test Cases'!$B$5:$B$81,A10,'Test Cases'!$H$5:$H$81,"PASS") -> 0 | F10: =COUNTIFS('Test Cases'!$B$5:$B$81,A10,'Test Cases'!$H$5:$H$81,"FAIL") -> 0
A11: Admin — Delete controls | B11: =COUNTIF('Test Cases'!$B$5:$B$81,A11) -> 6 | C11: =COUNTIFS('Test Cases'!$B$5:$B$81,A11,'Test Cases'!$C$5:$C$81,"P1") -> 4 | D11: =COUNTIFS('Test Cases'!$B$5:$B$81,A11,'Test Cases'!$H$5:$H$81,"<>") -> 0 | E11: =COUNTIFS('Test Cases'!$B$5:$B$81,A11,'Test Cases'!$H$5:$H$81,"PASS") -> 0 | F11: =COUNTIFS('Test Cases'!$B$5:$B$81,A11,'Test Cases'!$H$5:$H$81,"FAIL") -> 0
A12: Buy page — Coupon visibility | B12: =COUNTIF('Test Cases'!$B$5:$B$81,A12) -> 4 | C12: =COUNTIFS('Test Cases'!$B$5:$B$81,A12,'Test Cases'!$C$5:$C$81,"P1") -> 2 | D12: =COUNTIFS('Test Cases'!$B$5:$B$81,A12,'Test Cases'!$H$5:$H$81,"<>") -> 0 | E12: =COUNTIFS('Test Cases'!$B$5:$B$81,A12,'Test Cases'!$H$5:$H$81,"PASS") -> 0 | F12: =COUNTIFS('Test Cases'!$B$5:$B$81,A12,'Test Cases'!$H$5:$H$81,"FAIL") -> 0
A13: Central — Dunning fix (live) | B13: =COUNTIF('Test Cases'!$B$5:$B$81,A13) -> 3 | C13: =COUNTIFS('Test Cases'!$B$5:$B$81,A13,'Test Cases'!$C$5:$C$81,"P1") -> 2 | D13: =COUNTIFS('Test Cases'!$B$5:$B$81,A13,'Test Cases'!$H$5:$H$81,"<>") -> 0 | E13: =COUNTIFS('Test Cases'!$B$5:$B$81,A13,'Test Cases'!$H$5:$H$81,"PASS") -> 0 | F13: =COUNTIFS('Test Cases'!$B$5:$B$81,A13,'Test Cases'!$H$5:$H$81,"FAIL") -> 0
A14: Central — Branding & misc | B14: =COUNTIF('Test Cases'!$B$5:$B$81,A14) -> 4 | C14: =COUNTIFS('Test Cases'!$B$5:$B$81,A14,'Test Cases'!$C$5:$C$81,"P1") -> 2 | D14: =COUNTIFS('Test Cases'!$B$5:$B$81,A14,'Test Cases'!$H$5:$H$81,"<>") -> 0 | E14: =COUNTIFS('Test Cases'!$B$5:$B$81,A14,'Test Cases'!$H$5:$H$81,"PASS") -> 0 | F14: =COUNTIFS('Test Cases'!$B$5:$B$81,A14,'Test Cases'!$H$5:$H$81,"FAIL") -> 0
A15: Product — Login & seeder fix | B15: =COUNTIF('Test Cases'!$B$5:$B$81,A15) -> 3 | C15: =COUNTIFS('Test Cases'!$B$5:$B$81,A15,'Test Cases'!$C$5:$C$81,"P1") -> 3 | D15: =COUNTIFS('Test Cases'!$B$5:$B$81,A15,'Test Cases'!$H$5:$H$81,"<>") -> 0 | E15: =COUNTIFS('Test Cases'!$B$5:$B$81,A15,'Test Cases'!$H$5:$H$81,"PASS") -> 0 | F15: =COUNTIFS('Test Cases'!$B$5:$B$81,A15,'Test Cases'!$H$5:$H$81,"FAIL") -> 0
A16: Product — Email / SMTP settings | B16: =COUNTIF('Test Cases'!$B$5:$B$81,A16) -> 7 | C16: =COUNTIFS('Test Cases'!$B$5:$B$81,A16,'Test Cases'!$C$5:$C$81,"P1") -> 5 | D16: =COUNTIFS('Test Cases'!$B$5:$B$81,A16,'Test Cases'!$H$5:$H$81,"<>") -> 0 | E16: =COUNTIFS('Test Cases'!$B$5:$B$81,A16,'Test Cases'!$H$5:$H$81,"PASS") -> 0 | F16: =COUNTIFS('Test Cases'!$B$5:$B$81,A16,'Test Cases'!$H$5:$H$81,"FAIL") -> 0
A17: Product — Forgot password (OTP) | B17: =COUNTIF('Test Cases'!$B$5:$B$81,A17) -> 9 | C17: =COUNTIFS('Test Cases'!$B$5:$B$81,A17,'Test Cases'!$C$5:$C$81,"P1") -> 5 | D17: =COUNTIFS('Test Cases'!$B$5:$B$81,A17,'Test Cases'!$H$5:$H$81,"<>") -> 0 | E17: =COUNTIFS('Test Cases'!$B$5:$B$81,A17,'Test Cases'!$H$5:$H$81,"PASS") -> 0 | F17: =COUNTIFS('Test Cases'!$B$5:$B$81,A17,'Test Cases'!$H$5:$H$81,"FAIL") -> 0
A18: TOTAL | B18: =SUM(B6:B17) -> 77 | C18: =SUM(C6:C17) -> 55 | D18: =SUM(D6:D17) -> 0 | E18: =SUM(E6:E17) -> 0 | F18: =SUM(F6:F17) -> 0
