Workbook

Sheet BF Execution
A1: SmartEPT — Business Flow Testing Tracker (BF-01…BF-14)
A2: Fill yellow columns only: Status = PASS / FAIL / BLOCKED · Tested By = your name · Remarks = evidence link / defect. Any FAIL in BF-01…BF-07 → report to Ejaz sir immediately.
A4: Scenario | B4: Step | C4: Actor | D4: Action | E4: Expected | F4: Status | G4: Tested By | H4: Remarks
A5: BF-01 — Visitor → Lead (marketing funnel) | B5: 1 | C5: Visitor | D5: Open smartept.com fresh (incognito) | E5: Landing loads; hero price = first-band price; no ™/® anywhere
A6: BF-01 — Visitor → Lead (marketing funnel) | B6: 2 | C6: Visitor | D6: Play with pricing slider, On-premises tab: 41 / 61 / 201 users | E6: ₹33,250 / ₹44,400 / "Custom quotation" — matches /buy exactly
A7: BF-01 — Visitor → Lead (marketing funnel) | B7: 3 | C7: Visitor | D7: Fill the WhatsApp lead form (name, company, phone, devices, plan) and send | E7: WhatsApp chat opens pre-filled
A8: BF-01 — Visitor → Lead (marketing funnel) | B8: 4 | C8: Sales | D8: Check Central → Leads and the sales inbox | E8: Lead recorded with devices + message; instant email to sales received
A9: BF-01 — Visitor → Lead (marketing funnel) | B9: 5 | C9: Sales | D9: Update lead status/notes | E9: Pipeline reflects the change
A10: BF-02 — Visitor → Free Trial (OTP-gated) | B10: 1 | C10: Prospect | D10: Landing → Start free trial; fill form with NEW email, own password | E10: Step 2 appears: "We emailed a 6-digit code…"
A11: BF-02 — Visitor → Free Trial (OTP-gated) | B11: 2 | C11: Tester | D11: Check Central admin BEFORE verifying | E11: **NO tenant / portal user exists yet**
A12: BF-02 — Visitor → Free Trial (OTP-gated) | B12: 3 | C12: Prospect | D12: Enter a WRONG code | E12: Clear error; still nothing created
A13: BF-02 — Visitor → Free Trial (OTP-gated) | B13: 4 | C13: Prospect | D13: Enter the emailed code | E13: Trial activates; auto-login to client portal
A14: BF-02 — Visitor → Free Trial (OTP-gated) | B14: 5 | C14: Tester | D14: Verify in Central | E14: Tenant status trial, deployment cloud, terms timestamped; owner user email-verified
A15: BF-02 — Visitor → Free Trial (OTP-gated) | B15: 6 | C15: Tester | D15: Check the lead/trial views | E15: Trial visible to sales from day one
A16: BF-02 — Visitor → Free Trial (OTP-gated) | B16: 7 | C16: Tester | D16: (Time-shift or wait) trial reminders | E16: Emails at 3 / 1 / 0 days before expiry, deduplicated
... A72: BF-14 — Identity & Communications Backbone | B72: 6 | C72: Tester | D72: Every mail sent above | E72: Corresponding `mail_logs` row (sent/failed) exists

Sheet Summary
A1: Business Flow — Sign-off Summary
A2: Sign-off rule: BF-01…BF-07 fully PASS + no open P1 = business flow approved for launch.
A4: Scenario | B4: Steps | C4: Executed | D4: Passed | E4: Failed
A5: BF-01 — Visitor → Lead (marketing funnel) | B5: =COUNTIF('BF Execution'!$A$5:$A$72,A5) -> 5 | C5: =COUNTIFS('BF Execution'!$A$5:$A$72,A5,'BF Execution'!$F$5:$F$72,"<>") -> 0 | D5: =COUNTIFS('BF Execution'!$A$5:$A$72,A5,'BF Execution'!$F$5:$F$72,"PASS") -> 0 | E5: =COUNTIFS('BF Execution'!$A$5:$A$72,A5,'BF Execution'!$F$5:$F$72,"FAIL") -> 0
A6: BF-02 — Visitor → Free Trial (OTP-gated) | B6: =COUNTIF('BF Execution'!$A$5:$A$72,A6) -> 7 | C6: =COUNTIFS('BF Execution'!$A$5:$A$72,A6,'BF Execution'!$F$5:$F$72,"<>") -> 0 | D6: =COUNTIFS('BF Execution'!$A$5:$A$72,A6,'BF Execution'!$F$5:$F$72,"PASS") -> 0 | E6: =COUNTIFS('BF Execution'!$A$5:$A$72,A6,'BF Execution'!$F$5:$F$72,"FAIL") -> 0
A7: BF-03 — Trial → Paid Cloud (conversion + provisioning + agent) | B7: =COUNTIF('BF Execution'!$A$5:$A$72,A7) -> 7 | C7: =COUNTIFS('BF Execution'!$A$5:$A$72,A7,'BF Execution'!$F$5:$F$72,"<>") -> 0 | D7: =COUNTIFS('BF Execution'!$A$5:$A$72,A7,'BF Execution'!$F$5:$F$72,"PASS") -> 0 | E7: =COUNTIFS('BF Execution'!$A$5:$A$72,A7,'BF Execution'!$F$5:$F$72,"FAIL") -> 0
A8: BF-04 — Visitor → Direct Perpetual Buy → On-Prem Install → .lic ACTIVE | B8: =COUNTIF('BF Execution'!$A$5:$A$72,A8) -> 9 | C8: =COUNTIFS('BF Execution'!$A$5:$A$72,A8,'BF Execution'!$F$5:$F$72,"<>") -> 0 | D8: =COUNTIFS('BF Execution'!$A$5:$A$72,A8,'BF Execution'!$F$5:$F$72,"PASS") -> 0 | E8: =COUNTIFS('BF Execution'!$A$5:$A$72,A8,'BF Execution'!$F$5:$F$72,"FAIL") -> 0
A9: BF-05 — International USD Buy (export invoice) | B9: =COUNTIF('BF Execution'!$A$5:$A$72,A9) -> 3 | C9: =COUNTIFS('BF Execution'!$A$5:$A$72,A9,'BF Execution'!$F$5:$F$72,"<>") -> 0 | D9: =COUNTIFS('BF Execution'!$A$5:$A$72,A9,'BF Execution'!$F$5:$F$72,"PASS") -> 0 | E9: =COUNTIFS('BF Execution'!$A$5:$A$72,A9,'BF Execution'!$F$5:$F$72,"FAIL") -> 0
A10: BF-06 — Quotation Road (portal quote → management pays) | B10: =COUNTIF('BF Execution'!$A$5:$A$72,A10) -> 5 | C10: =COUNTIFS('BF Execution'!$A$5:$A$72,A10,'BF Execution'!$F$5:$F$72,"<>") -> 0 | D10: =COUNTIFS('BF Execution'!$A$5:$A$72,A10,'BF Execution'!$F$5:$F$72,"PASS") -> 0 | E10: =COUNTIFS('BF Execution'!$A$5:$A$72,A10,'BF Execution'!$F$5:$F$72,"FAIL") -> 0
A11: BF-07 — Sales-Assisted Credit Client | B11: =COUNTIF('BF Execution'!$A$5:$A$72,A11) -> 5 | C11: =COUNTIFS('BF Execution'!$A$5:$A$72,A11,'BF Execution'!$F$5:$F$72,"<>") -> 0 | D11: =COUNTIFS('BF Execution'!$A$5:$A$72,A11,'BF Execution'!$F$5:$F$72,"PASS") -> 0 | E11: =COUNTIFS('BF Execution'!$A$5:$A$72,A11,'BF Execution'!$F$5:$F$72,"FAIL") -> 0
A12: BF-08 — Coupons & Discounts on the Money Path | B12: =COUNTIF('BF Execution'!$A$5:$A$72,A12) -> 5 | C12: =COUNTIFS('BF Execution'!$A$5:$A$72,A12,'BF Execution'!$F$5:$F$72,"<>") -> 0 | D12: =COUNTIFS('BF Execution'!$A$5:$A$72,A12,'BF Execution'!$F$5:$F$72,"PASS") -> 0 | E12: =COUNTIFS('BF Execution'!$A$5:$A$72,A12,'BF Execution'!$F$5:$F$72,"FAIL") -> 0
A13: BF-09 — Renewal, Dunning & Suspension Ladder | B13: =COUNTIF('BF Execution'!$A$5:$A$72,A13) -> 6 | C13: =COUNTIFS('BF Execution'!$A$5:$A$72,A13,'BF Execution'!$F$5:$F$72,"<>") -> 0 | D13: =COUNTIFS('BF Execution'!$A$5:$A$72,A13,'BF Execution'!$F$5:$F$72,"PASS") -> 0 | E13: =COUNTIFS('BF Execution'!$A$5:$A$72,A13,'BF Execution'!$F$5:$F$72,"FAIL") -> 0
A14: BF-10 — Growth: Upgrades | B14: =COUNTIF('BF Execution'!$A$5:$A$72,A14) -> 2 | C14: =COUNTIFS('BF Execution'!$A$5:$A$72,A14,'BF Execution'!$F$5:$F$72,"<>") -> 0 | D14: =COUNTIFS('BF Execution'!$A$5:$A$72,A14,'BF Execution'!$F$5:$F$72,"PASS") -> 0 | E14: =COUNTIFS('BF Execution'!$A$5:$A$72,A14,'BF Execution'!$F$5:$F$72,"FAIL") -> 0
A15: BF-11 — AMC Year-2 (On-Prem) | B15: =COUNTIF('BF Execution'!$A$5:$A$72,A15) -> 2 | C15: =COUNTIFS('BF Execution'!$A$5:$A$72,A15,'BF Execution'!$F$5:$F$72,"<>") -> 0 | D15: =COUNTIFS('BF Execution'!$A$5:$A$72,A15,'BF Execution'!$F$5:$F$72,"PASS") -> 0 | E15: =COUNTIFS('BF Execution'!$A$5:$A$72,A15,'BF Execution'!$F$5:$F$72,"FAIL") -> 0
A16: BF-12 — Hardware Change (release / shift machine) | B16: =COUNTIF('BF Execution'!$A$5:$A$72,A16) -> 3 | C16: =COUNTIFS('BF Execution'!$A$5:$A$72,A16,'BF Execution'!$F$5:$F$72,"<>") -> 0 | D16: =COUNTIFS('BF Execution'!$A$5:$A$72,A16,'BF Execution'!$F$5:$F$72,"PASS") -> 0 | E16: =COUNTIFS('BF Execution'!$A$5:$A$72,A16,'BF Execution'!$F$5:$F$72,"FAIL") -> 0
... A18: BF-14 — Identity & Communications Backbone | B18: =COUNTIF('BF Execution'!$A$5:$A$72,A18) -> 6 | C18: =COUNTIFS('BF Execution'!$A$5:$A$72,A18,'BF Execution'!$F$5:$F$72,"<>") -> 0 | D18: =COUNTIFS('BF Execution'!$A$5:$A$72,A18,'BF Execution'!$F$5:$F$72,"PASS") -> 0 | E18: =COUNTIFS('BF Execution'!$A$5:$A$72,A18,'BF Execution'!$F$5:$F$72,"FAIL") -> 0
