Workbook

Sheet How to use
B2: SmartEPT — Regression Re-Test Pack
B3: Last 10 sessions across Central, Product (SmartEPT server/console) and the desktop Agent
B4: Version 1.0 · 27 July 2026 · Ametecs India Private Limited
B6: How to use this pack
B7: 1. Work the 'Test Cases' tab | C7: One row per case. Read Preconditions, follow Steps, compare against Expected Result.
B8: 2. Record the outcome | C8: In the Result column pick Pass / Fail / Blocked / Not run from the dropdown. Add your name, the date, and any Notes (for a Fail, paste the exact error text).
B9: 3. Watch the Summary tab | C9: It totals Pass/Fail/Blocked/Not-run per session automatically and shows a pass rate.
B10: Priority key | C10: P1 = critical (money / data / licensing) · P2 = high · P3 = medium.
B11: Environment note | C11: Owner must first run the pending migrations + rebuild the agent + confirm the OS scheduler runs 'php artisan schedule:run' every minute, or scheduler-dependent cases (meetings auto-close, biometric sync, archives, dunning) will look failed when they are only un-run.
B12: Repos under test | C12: Central = C:\laragon\www\smartept-central · Product = C:\laragon\www\smartept · Agent = ...\Projects\SmartEPT\agent.
B14: Example filled row
B15: Case ID | C15: Session | D15: Area | E15: Module | F15: Priority | G15: Title | H15: Preconditions | I15: Steps | J15: Expected | K15: Result | L15: Tester | M15: Date | N15: Notes
B16: S1-01 | C16: Pricing v2 Finalise (27-Jul) | D16: Central | E16: Licensing / Grandfather | F16: P1 | G16: Legacy licence renewal is price-capped | H16: ... | I16: ... | J16: ... | K16: Pass | L16: A. Tester | M16: 27-Jul-2026 | N16: Cap line showed -₹4,200; total within 20%.

Sheet Test Cases
A1: SmartEPT — Regression Re-Test Cases (last 10 sessions)
A2: Case ID | B2: Session | C2: Area | D2: Module | E2: Pri | F2: Title | G2: Preconditions | H2: Steps | I2: Expected Result | J2: Result | K2: Tester | L2: Date | M2: Notes
A3: S1-01 | B3: Pricing v2 Finalise (27-Jul) | C3: Central | D3: Licensing / Grandfather | E3: P1 | F3: Legacy licence renewal is price-capped | G3: Migration 2026_07_27_000200 run; an existing (pre-v2) licence exists with pricing_model=legacy and a legacy_baseline_inr. | H3: Open the legacy client's licence and raise a renewal (portal Renew or admin). Inspect the quote lines. | I3: A 'Loyalty price protection' negative line appears; the ex-GST subtotal is capped at baseline x (1 + grandfather cap % ), so the total cannot exceed ~20% over the previous rate. | J3: Not run
A4: S1-02 | B4: Pricing v2 Finalise (27-Jul) | C4: Central | D4: Licensing / Grandfather | E4: P2 | F4: Licence flips to v2 after the grandfathered renewal | G4: The capped renewal from S1-01 is paid. | H4: Pay the renewal order; then re-open the licence. | I4: pricing_model is now 'v2' and legacy_baseline_inr is cleared; a subsequent renewal is quoted at full v2 rate (no cap line). | J4: Not run
A5: S1-03 | B5: Pricing v2 Finalise (27-Jul) | C5: Central | D5: Licensing / Grandfather | E5: P3 | F5: New licence defaults to v2 (never grandfathered) | G5: Migration run. | H5: Issue a brand-new licence to a new tenant. | I5: pricing_model = v2 by default; no cap logic applies on its renewals. | J5: Not run
A6: S1-04 | B6: Pricing v2 Finalise (27-Jul) | C6: Central | D6: Orders / PO number | E6: P2 | F6: PO number captured on admin New Order/Quote | G6: Logged in as super/sales. | H6: Orders -> New Order/Quote; fill Client, users, enter a Client PO number; create the order. | I6: The order is created with the PO number stored (visible on the order and its quote print). | J6: Not run
A7: S1-05 | B7: Pricing v2 Finalise (27-Jul) | C7: Central | D7: Orders / PO number | E7: P3 | F7: PO number captured on client portal Buy | G7: Logged into the client portal. | H7: Buy screen -> enter users + a PO number -> raise a quotation. | I7: The quotation carries the PO number. | J7: Not run
A8: S1-06 | B8: Pricing v2 Finalise (27-Jul) | C8: Central | D8: Quote / Proforma | E8: P2 | F8: Quotation prints as 'Quotation / Proforma Invoice' with PO + validity | G8: An order/quote with a PO number exists. | H8: Open the order's Quotation/Proforma print (admin or portal). | I8: Title reads 'QUOTATION / PROFORMA INVOICE'; the PO number and a 'valid until <date>' line are shown; terms show the same validity date. | J8: Not run
A9: S1-07 | B9: Pricing v2 Finalise (27-Jul) | C9: Central | D9: Checkout / Expiry | E9: P1 | F9: Expired pay-link refuses payment (page) | G9: An order whose valid_until is in the past, with nothing paid. | H9: Open /pay/{number}/{token} for that order. | I9: The page shows 'This quotation has expired — contact sales' and offers no pay button. | J9: Not run
A10: S1-08 | B10: Pricing v2 Finalise (27-Jul) | C10: Central | D10: Checkout / Expiry | E10: P2 | F10: Expired quote refuses Razorpay & Stripe init | G10: Expired unpaid order as above; a gateway enabled. | H10: Attempt to start Razorpay and Stripe payment on the expired order. | I10: Both refuse with HTTP 410 and a 'quotation has expired' message; no charge is initiated. | J10: Not run
A11: S1-09 | B11: Pricing v2 Finalise (27-Jul) | C11: Central | D11: Checkout / Expiry | E11: P3 | F11: A paid/part-paid (credit) order stays payable after date | G11: An order that is already part-paid/provisioned and past valid_until. | H11: Open its pay-link. | I11: The link stays live and collects the remaining balance (expiry only blocks untouched quotes). | J11: Not run
A12: S1-10 | B12: Pricing v2 Finalise (27-Jul) | C12: Central | D12: Plans / Cleanup | E12: P2 | F12: Plans table shows v2 perpetual bands, not legacy per-device | G12: Logged in as super; PricingV2Seeder run. | H12: Open Plans & Pricing. | I12: The 'Perpetual (by users)' column lists the user-band prices; the old 'Perpetual/Device' and 'Server Licence' columns are gone. | J12: Not run
A13: S1-11 | B13: Pricing v2 Finalise (27-Jul) | C13: Central | D13: Plans / Cleanup | E13: P3 | F13: Edit-plan modal has no legacy per-device inputs; save works | G13: Super role. | H13: Plans -> Edit the SmartEPT plan; change the annual rate; Save. | I13: No 'Perpetual/device' or 'Server licence' inputs; the read-only perpetual bands show; Save succeeds and the annual rate updates. | J13: Not run
A14: S1-12 | B14: Pricing v2 Finalise (27-Jul) | C14: Central | D14: Orders / Plan | E14: P3 | F14: New Order form offers the single SmartEPT plan | G14: Super/sales. | H14: Orders -> New Order/Quote; open the Plan dropdown. | I14: Only 'SmartEPT — all features' is offered (no Core/Professional/Enterprise). | J14: Not run
... A90: S10-08 | B90: 1.0 Launch marathon (20-Jul) | C90: Product | D90: Violations | E90: P3 | F90: Violation 'View evidence' matches the trigger | G90: A BLOCKED_APP/BLOCKED_SITE violation with on-blocked screenshot policy ON. | H90: Open 'View evidence' for the violation. | I90: The shown screenshot matches the offending app/site by trigger reason, not nearest-time. | J90: Not run

Sheet Summary
B2: Re-Test Summary
B3: Counts recalculate automatically from the Test Cases tab as testers fill in Results.
B5: Session | C5: Total | D5: Pass | E5: Fail | F5: Blocked | G5: Not run | H5: Pass %
B6: S1 · Pricing v2 Finalise (27-Jul) | C6: =COUNTIF('Test Cases'!$A$3:$A$90,"S1-*") -> 13 | D6: =COUNTIFS('Test Cases'!$A$3:$A$90,"S1-*",'Test Cases'!$J$3:$J$90,"Pass") -> 0 | E6: =COUNTIFS('Test Cases'!$A$3:$A$90,"S1-*",'Test Cases'!$J$3:$J$90,"Fail") -> 0 | F6: =COUNTIFS('Test Cases'!$A$3:$A$90,"S1-*",'Test Cases'!$J$3:$J$90,"Blocked") -> 0 | G6: =COUNTIFS('Test Cases'!$A$3:$A$90,"S1-*",'Test Cases'!$J$3:$J$90,"Not run") -> 13 | H6: =IFERROR(D6/C6,0) -> 0
B7: S2 · Pricing v2 (26-Jul) | C7: =COUNTIF('Test Cases'!$A$3:$A$90,"S2-*") -> 11 | D7: =COUNTIFS('Test Cases'!$A$3:$A$90,"S2-*",'Test Cases'!$J$3:$J$90,"Pass") -> 0 | E7: =COUNTIFS('Test Cases'!$A$3:$A$90,"S2-*",'Test Cases'!$J$3:$J$90,"Fail") -> 0 | F7: =COUNTIFS('Test Cases'!$A$3:$A$90,"S2-*",'Test Cases'!$J$3:$J$90,"Blocked") -> 0 | G7: =COUNTIFS('Test Cases'!$A$3:$A$90,"S2-*",'Test Cases'!$J$3:$J$90,"Not run") -> 11 | H7: =IFERROR(D7/C7,0) -> 0
B8: S3 · Bug round 25-Jul | C8: =COUNTIF('Test Cases'!$A$3:$A$90,"S3-*") -> 11 | D8: =COUNTIFS('Test Cases'!$A$3:$A$90,"S3-*",'Test Cases'!$J$3:$J$90,"Pass") -> 0 | E8: =COUNTIFS('Test Cases'!$A$3:$A$90,"S3-*",'Test Cases'!$J$3:$J$90,"Fail") -> 0 | F8: =COUNTIFS('Test Cases'!$A$3:$A$90,"S3-*",'Test Cases'!$J$3:$J$90,"Blocked") -> 0 | G8: =COUNTIFS('Test Cases'!$A$3:$A$90,"S3-*",'Test Cases'!$J$3:$J$90,"Not run") -> 11 | H8: =IFERROR(D8/C8,0) -> 0
B9: S4 · Employee Archive (24-Jul) | C9: =COUNTIF('Test Cases'!$A$3:$A$90,"S4-*") -> 6 | D9: =COUNTIFS('Test Cases'!$A$3:$A$90,"S4-*",'Test Cases'!$J$3:$J$90,"Pass") -> 0 | E9: =COUNTIFS('Test Cases'!$A$3:$A$90,"S4-*",'Test Cases'!$J$3:$J$90,"Fail") -> 0 | F9: =COUNTIFS('Test Cases'!$A$3:$A$90,"S4-*",'Test Cases'!$J$3:$J$90,"Blocked") -> 0 | G9: =COUNTIFS('Test Cases'!$A$3:$A$90,"S4-*",'Test Cases'!$J$3:$J$90,"Not run") -> 6 | H9: =IFERROR(D9/C9,0) -> 0
B10: S5 · Bug round 24-Jul | C10: =COUNTIF('Test Cases'!$A$3:$A$90,"S5-*") -> 10 | D10: =COUNTIFS('Test Cases'!$A$3:$A$90,"S5-*",'Test Cases'!$J$3:$J$90,"Pass") -> 0 | E10: =COUNTIFS('Test Cases'!$A$3:$A$90,"S5-*",'Test Cases'!$J$3:$J$90,"Fail") -> 0 | F10: =COUNTIFS('Test Cases'!$A$3:$A$90,"S5-*",'Test Cases'!$J$3:$J$90,"Blocked") -> 0 | G10: =COUNTIFS('Test Cases'!$A$3:$A$90,"S5-*",'Test Cases'!$J$3:$J$90,"Not run") -> 10 | H10: =IFERROR(D10/C10,0) -> 0
B11: S6 · Central QA Round-2 (23-Jul) | C11: =COUNTIF('Test Cases'!$A$3:$A$90,"S6-*") -> 5 | D11: =COUNTIFS('Test Cases'!$A$3:$A$90,"S6-*",'Test Cases'!$J$3:$J$90,"Pass") -> 0 | E11: =COUNTIFS('Test Cases'!$A$3:$A$90,"S6-*",'Test Cases'!$J$3:$J$90,"Fail") -> 0 | F11: =COUNTIFS('Test Cases'!$A$3:$A$90,"S6-*",'Test Cases'!$J$3:$J$90,"Blocked") -> 0 | G11: =COUNTIFS('Test Cases'!$A$3:$A$90,"S6-*",'Test Cases'!$J$3:$J$90,"Not run") -> 5 | H11: =IFERROR(D11/C11,0) -> 0
B12: S7 · QA Defect Phase (23-Jul) | C12: =COUNTIF('Test Cases'!$A$3:$A$90,"S7-*") -> 11 | D12: =COUNTIFS('Test Cases'!$A$3:$A$90,"S7-*",'Test Cases'!$J$3:$J$90,"Pass") -> 0 | E12: =COUNTIFS('Test Cases'!$A$3:$A$90,"S7-*",'Test Cases'!$J$3:$J$90,"Fail") -> 0 | F12: =COUNTIFS('Test Cases'!$A$3:$A$90,"S7-*",'Test Cases'!$J$3:$J$90,"Blocked") -> 0 | G12: =COUNTIFS('Test Cases'!$A$3:$A$90,"S7-*",'Test Cases'!$J$3:$J$90,"Not run") -> 11 | H12: =IFERROR(D12/C12,0) -> 0
B13: S8 · Next-Phase programme (21-Jul) | C13: =COUNTIF('Test Cases'!$A$3:$A$90,"S8-*") -> 9 | D13: =COUNTIFS('Test Cases'!$A$3:$A$90,"S8-*",'Test Cases'!$J$3:$J$90,"Pass") -> 0 | E13: =COUNTIFS('Test Cases'!$A$3:$A$90,"S8-*",'Test Cases'!$J$3:$J$90,"Fail") -> 0 | F13: =COUNTIFS('Test Cases'!$A$3:$A$90,"S8-*",'Test Cases'!$J$3:$J$90,"Blocked") -> 0 | G13: =COUNTIFS('Test Cases'!$A$3:$A$90,"S8-*",'Test Cases'!$J$3:$J$90,"Not run") -> 9 | H13: =IFERROR(D13/C13,0) -> 0
B14: S9 · Landing Revamp (22-Jul) | C14: =COUNTIF('Test Cases'!$A$3:$A$90,"S9-*") -> 4 | D14: =COUNTIFS('Test Cases'!$A$3:$A$90,"S9-*",'Test Cases'!$J$3:$J$90,"Pass") -> 0 | E14: =COUNTIFS('Test Cases'!$A$3:$A$90,"S9-*",'Test Cases'!$J$3:$J$90,"Fail") -> 0 | F14: =COUNTIFS('Test Cases'!$A$3:$A$90,"S9-*",'Test Cases'!$J$3:$J$90,"Blocked") -> 0 | G14: =COUNTIFS('Test Cases'!$A$3:$A$90,"S9-*",'Test Cases'!$J$3:$J$90,"Not run") -> 4 | H14: =IFERROR(D14/C14,0) -> 0
B15: S10 · 1.0 Launch marathon (20-Jul) | C15: =COUNTIF('Test Cases'!$A$3:$A$90,"S10-*") -> 8 | D15: =COUNTIFS('Test Cases'!$A$3:$A$90,"S10-*",'Test Cases'!$J$3:$J$90,"Pass") -> 0 | E15: =COUNTIFS('Test Cases'!$A$3:$A$90,"S10-*",'Test Cases'!$J$3:$J$90,"Fail") -> 0 | F15: =COUNTIFS('Test Cases'!$A$3:$A$90,"S10-*",'Test Cases'!$J$3:$J$90,"Blocked") -> 0 | G15: =COUNTIFS('Test Cases'!$A$3:$A$90,"S10-*",'Test Cases'!$J$3:$J$90,"Not run") -> 8 | H15: =IFERROR(D15/C15,0) -> 0
B16: TOTAL | C16: =SUM(C6:C15) -> 88 | D16: =SUM(D6:D15) -> 0 | E16: =SUM(E6:E15) -> 0 | F16: =SUM(F6:F15) -> 0 | G16: =SUM(G6:G15) -> 88 | H16: =IFERROR(D16/C16,0) -> 0
B18: P1 critical cases | C18: =COUNTIF('Test Cases'!$E$3:$E$90,"P1") -> 15 | D18: P1 passed | E18: =COUNTIFS('Test Cases'!$E$3:$E$90,"P1",'Test Cases'!$J$3:$J$90,"Pass") -> 0
