Workbook

Sheet Cover
B2: SmartEPT — Central (Super Admin)
B3: Software Test Cases & QA Verification Pack
B4: M/s. AMETECS INDIA PRIVATE LIMITED · Employee Productivity Tracking & Intelligence
B6: Document | C6: SmartEPT-Central-Test-Cases
B7: Revision | C7: rev001
B8: Date | C8: 23 July 2026
B9: Build / commit | C9: main @ 0377f00
B10: Scope | C10: Central super-admin console — all modules + QA round-2 fixes
B11: Prepared by | C11: SmartEPT Dev (Ametecs)
B12: Total test cases | C12: 113
B13: Priority key | C13: P1 = critical · P2 = major · P3 = minor
B14: Status values | C14: Pass · Fail · Blocked · Not Run (dropdown in each row)
B16: How to use this workbook
B17: • 'Bug-Fix Verification (R2)' — retest the 5 issues your team reported on 23-Jul (highest priority).
B18: • 'Test Cases' — full module-by-module coverage of the Central console.
B19: • Fill Actual Result + Status (dropdown) per row; add Notes for any Fail/Blocked.
B20: • 'Summary' auto-counts progress by module and priority once you set Status.

Sheet Bug-Fix Verification (R2)
A1: QA Round-2 — Verification of the 5 issues reported 23-Jul-2026 (fixed in main @ 0377f00)
A2: TC ID | B2: Module | C2: Sub-Area | D2: Title / Scenario | E2: Type | F2: Priority | G2: Preconditions | H2: Test Steps | I2: Test Data | J2: Expected Result | K2: Actual Result | L2: Status | M2: Notes
A3: BF-01 | B3: Licences | C3: Billing period | D3: Issue licence with QUARTERLY period saves without error | E3: Regression | F3: P1 | G3: Logged in as Super admin; at least one client + plan exist. | H3: 1. Go to Licences → + Issue Licence 2. Pick a client and plan 3. Set Billing period = Quarterly — 3 months 4. Set Kind=Subscription, a device limit, click Issue Licence | I3: Client=any, Plan=Professional, Billing=Quarterly, Devices=10 | J3: Licence is created; toast shows the new key; NO 'data truncated'/server error. Expiry = today + 3 months.
A4: BF-02 | B4: Licences | C4: Billing period | D4: Issue licence with HALF-YEARLY (6-month) period saves without error | E4: Regression | F4: P1 | G4: Super admin; client + plan exist. | H4: 1. Licences → + Issue Licence 2. Billing period = Half-yearly — 6 months 3. Complete and Issue | I4: Billing=Half-yearly, Devices=10 | J4: Licence created, key shown, no error. Expiry = today + 6 months.
A5: BF-03 | B5: Licences | C5: Billing period | D5: Edit an existing licence's billing cycle to Quarterly/Half-yearly | E5: Regression | F5: P1 | G5: An active licence exists. | H5: 1. Licences → Edit on a licence 2. Change Billing cycle = Half-yearly 3. Save changes | I5: Billing=Half-yearly | J5: Save succeeds, no error, list reflects the change on reload.
A6: BF-04 | B6: Orders | C6: Trial→Paid partial | D6: Convert Trial to Paid and record a PARTIAL payment on a Quarterly order | E6: Regression | F6: P1 | G6: A tenant in Trial status exists. | H6: 1. Trials → Convert to Paid (opens New Order) 2. Choose Billing = Quarterly, create the order 3. On the order, Record Payment → Partial 4. Enter part amount, method, credit due date, Save & provision | I6: Billing=Quarterly, Total e.g. ₹11,800, Partial=₹5,000, Due date=+15 days | J6: Payment records, licence provisions as ACTIVE, invoice issued as DUE, balance = total − part. NO error at the partial step.
A7: BF-05 | B7: Support | C7: Reply not erased | D7: Adding a second reply keeps the first reply (no overwrite) | E7: Regression | F7: P1 | G7: A ticket exists with one admin reply already sent. | H7: 1. Support → open the ticket 2. Confirm the earlier reply shows in the thread (read-only) 3. Type a NEW reply in the empty box 4. Save & send | I7: Reply 1 already present; Reply 2 = new text | J7: Both replies appear in the thread with author + time. The earlier reply is NOT editable and NOT erased.
A8: BF-06 | B8: Support | C8: Timeline & author | D8: Status change and responder are recorded in the timeline | E8: Regression | F8: P1 | G8: An open ticket exists. | H8: 1. Open the ticket 2. Change status open→in_progress and add a reply 3. Save & send 4. Re-open the ticket | I8: Status open→in_progress; reply text | J8: Timeline shows a 'changed status open → in progress' entry and the reply, each with the staff member's name and IST time.
A9: BF-07 | B9: Support | C9: Local time | D9: Ticket times display in IST, not UTC | E9: Regression | F9: P1 | G9: At least one ticket raised in the last hour. | H9: 1. Open Support list 2. Note the Raised time 3. Compare with the wall clock (IST) | I9: Current IST time | J9: Raised/replied times match IST (UTC+5:30), formatted like '23 Jul 2026, 08:15 PM'.
A10: BF-08 | B10: Downloads | C10: Upload limit | D10: Upload a 100MB+ installer from the console | E10: Regression | F10: P1 | G10: Super admin; php.ini/.user.ini limit raised to 256M and PHP restarted. | H10: 1. Settings has taken effect (Downloads screen shows 'Max upload ... 256M') 2. Downloads → add/replace file → choose a 100–150MB installer 3. Save | I10: installer .exe ≈ 120MB | J10: Upload completes; artifact shows the real filename and size; no 'file too large' error.
A11: BF-09 | B11: Orders | C11: Licence shown | D11: Orders & Payment lists the linked Licence | E11: Regression | F11: P1 | G11: At least one paid/provisioned order exists. | H11: 1. Go to Orders & Payment 2. Inspect the new Licence column | I11: any provisioned order | J11: Each order that issued/renewed a licence shows its licence key (with status if not active); orders without a licence show —.
A12: BF-10 | B12: Support | C12: Migration integrity | D12: Existing tickets keep their original message + reply after upgrade | E12: Regression | F12: P1 | G12: Migrations 000700/000800 run on a DB that already had tickets. | H12: 1. Open a ticket that existed before the update | I12: pre-existing ticket | J12: The client's original message and any prior admin reply appear as the first entries in the new thread (nothing lost).

Sheet Test Cases
A1: TC ID | B1: Module | C1: Sub-Area | D1: Title / Scenario | E1: Type | F1: Priority | G1: Preconditions | H1: Test Steps | I1: Test Data | J1: Expected Result | K1: Actual Result | L1: Status | M1: Notes
A2: TC-A01 | B2: Access | C2: Admin login | D2: Valid super-admin login | E2: Functional | F2: P1 | G2: Valid super-admin account exists. | H2: 1. Open /admin/login 2. Enter correct email & password 3. Submit | I2: valid creds | J2: Redirected to console; session established; nav shows all modules.
A3: TC-A02 | B3: Access | C3: Admin login | D3: Wrong password rejected | E3: Negative | F3: P1 | G3: Account exists. | H3: 1. Open /admin/login 2. Enter valid email, wrong password 3. Submit | I3: bad password | J3: Login refused with a friendly error; no session created.
A4: TC-A03 | B4: Access | C4: Rate limit | D4: Login throttle after repeated failures | E4: Security | F4: P2 | G4: — | H4: 1. Attempt login 11 times rapidly with wrong password | I4: throttle:10,1 | J4: After the limit, requests are throttled (429) for the window.
A5: TC-A04 | B5: Access | C5: Logout | D5: Logout ends the session | E5: Functional | F5: P2 | G5: Logged in. | H5: 1. Click logout | I5: — | J5: Session cleared; visiting console redirects to login.
A6: TC-A05 | B6: Access | C6: Guard | D6: Unauthenticated access blocked | E6: Security | F6: P1 | G6: Logged out. | H6: 1. Directly open /admin or an /admin/api endpoint | I6: — | J6: Redirected to login / 401; no data returned.
A7: TC-A06 | B7: Access | C7: Password | D7: Login is case-sensitive on password | E7: Negative | F7: P3 | G7: Account exists. | H7: 1. Enter correct email, password with altered case 2. Submit | I7: case-variant | J7: Login refused.
A8: TC-B01 | B8: Dashboard | C8: KPIs | D8: Dashboard loads revenue/MRR/trials/unpaid | E8: Functional | F8: P2 | G8: Some orders/trials exist. | H8: 1. Open Dashboard | I8: — | J8: Cards render: revenue this month, MRR, trials expiring 7d, unpaid orders — values match data.
A9: TC-B02 | B9: Dashboard | C9: Needs attention | D9: Counts equal trials expiring + unpaid orders | E9: Functional | F9: P3 | G9: — | H9: 1. Read 'Needs Attention' vs the two sub-counts | I9: — | J9: Needs Attention = trials_expiring_7d + orders_pending.
A10: TC-B03 | B10: Dashboard | C10: Recent orders | D10: Recent orders table shows latest first | E10: Functional | F10: P3 | G10: ≥1 order. | H10: 1. View recent orders on dashboard | I10: — | J10: Newest orders on top; number, client, total, status correct.
A11: TC-C01 | B11: Clients | C11: Create | D11: Create a new client/tenant | E11: Functional | F11: P1 | G11: Super/sales. | H11: 1. Clients → add tenant 2. Fill company, email, phone, deployment 3. Save | I11: company='Krishna NBFC' | J11: Tenant created and listed.
A12: TC-C02 | B12: Clients | C12: Validation | D12: Duplicate/invalid email rejected | E12: Negative | F12: P2 | G12: — | H12: 1. Create tenant with malformed email | I12: email='abc' | J12: Validation error; not saved.
A13: TC-C03 | B13: Clients | C13: View | D13: Open a client detail (licences, orders, storage) | E13: Functional | F13: P2 | G13: Client exists. | H13: 1. Clients → open a client | I13: — | J13: Detail shows company info, licences, orders, and actions (raise setup invoice etc.).
... A104: TC-V05 | B104: Cross | C104: Session | D104: Console persists across refresh; hard-refresh loads latest | E104: UI/UX | F104: P3 | G104: — | H104: 1. Hard refresh (Ctrl+Shift+R) | I104: — | J104: Latest console assets load; no stale cache issues.

Sheet Summary
B2: Coverage & Progress Summary
B4: Module | C4: Total | D4: P1 | E4: P2 | F4: P3 | G4: Pass | H4: Fail | I4: Blocked | J4: Not Run
B5: Access | C5: =COUNTIF('Test Cases'!$B:$B,"Access") -> 6 | D5: =COUNTIFS('Test Cases'!$B:$B,"Access",'Test Cases'!$F:$F,"P1") -> 3 | E5: =COUNTIFS('Test Cases'!$B:$B,"Access",'Test Cases'!$F:$F,"P2") -> 2 | F5: =COUNTIFS('Test Cases'!$B:$B,"Access",'Test Cases'!$F:$F,"P3") -> 1 | G5: =COUNTIFS('Test Cases'!$B:$B,"Access",'Test Cases'!$L:$L,"Pass") -> 0 | H5: =COUNTIFS('Test Cases'!$B:$B,"Access",'Test Cases'!$L:$L,"Fail") -> 0 | I5: =COUNTIFS('Test Cases'!$B:$B,"Access",'Test Cases'!$L:$L,"Blocked") -> 0 | J5: =COUNTIFS('Test Cases'!$B:$B,"Access",'Test Cases'!$L:$L,"Not Run") -> 0
B6: Dashboard | C6: =COUNTIF('Test Cases'!$B:$B,"Dashboard") -> 3 | D6: =COUNTIFS('Test Cases'!$B:$B,"Dashboard",'Test Cases'!$F:$F,"P1") -> 0 | E6: =COUNTIFS('Test Cases'!$B:$B,"Dashboard",'Test Cases'!$F:$F,"P2") -> 1 | F6: =COUNTIFS('Test Cases'!$B:$B,"Dashboard",'Test Cases'!$F:$F,"P3") -> 2 | G6: =COUNTIFS('Test Cases'!$B:$B,"Dashboard",'Test Cases'!$L:$L,"Pass") -> 0 | H6: =COUNTIFS('Test Cases'!$B:$B,"Dashboard",'Test Cases'!$L:$L,"Fail") -> 0 | I6: =COUNTIFS('Test Cases'!$B:$B,"Dashboard",'Test Cases'!$L:$L,"Blocked") -> 0 | J6: =COUNTIFS('Test Cases'!$B:$B,"Dashboard",'Test Cases'!$L:$L,"Not Run") -> 0
B7: Clients | C7: =COUNTIF('Test Cases'!$B:$B,"Clients") -> 5 | D7: =COUNTIFS('Test Cases'!$B:$B,"Clients",'Test Cases'!$F:$F,"P1") -> 1 | E7: =COUNTIFS('Test Cases'!$B:$B,"Clients",'Test Cases'!$F:$F,"P2") -> 3 | F7: =COUNTIFS('Test Cases'!$B:$B,"Clients",'Test Cases'!$F:$F,"P3") -> 1 | G7: =COUNTIFS('Test Cases'!$B:$B,"Clients",'Test Cases'!$L:$L,"Pass") -> 0 | H7: =COUNTIFS('Test Cases'!$B:$B,"Clients",'Test Cases'!$L:$L,"Fail") -> 0 | I7: =COUNTIFS('Test Cases'!$B:$B,"Clients",'Test Cases'!$L:$L,"Blocked") -> 0 | J7: =COUNTIFS('Test Cases'!$B:$B,"Clients",'Test Cases'!$L:$L,"Not Run") -> 0
B8: Licences | C8: =COUNTIF('Test Cases'!$B:$B,"Licences") -> 14 | D8: =COUNTIFS('Test Cases'!$B:$B,"Licences",'Test Cases'!$F:$F,"P1") -> 2 | E8: =COUNTIFS('Test Cases'!$B:$B,"Licences",'Test Cases'!$F:$F,"P2") -> 8 | F8: =COUNTIFS('Test Cases'!$B:$B,"Licences",'Test Cases'!$F:$F,"P3") -> 4 | G8: =COUNTIFS('Test Cases'!$B:$B,"Licences",'Test Cases'!$L:$L,"Pass") -> 0 | H8: =COUNTIFS('Test Cases'!$B:$B,"Licences",'Test Cases'!$L:$L,"Fail") -> 0 | I8: =COUNTIFS('Test Cases'!$B:$B,"Licences",'Test Cases'!$L:$L,"Blocked") -> 0 | J8: =COUNTIFS('Test Cases'!$B:$B,"Licences",'Test Cases'!$L:$L,"Not Run") -> 0
B9: Orders | C9: =COUNTIF('Test Cases'!$B:$B,"Orders") -> 15 | D9: =COUNTIFS('Test Cases'!$B:$B,"Orders",'Test Cases'!$F:$F,"P1") -> 3 | E9: =COUNTIFS('Test Cases'!$B:$B,"Orders",'Test Cases'!$F:$F,"P2") -> 9 | F9: =COUNTIFS('Test Cases'!$B:$B,"Orders",'Test Cases'!$F:$F,"P3") -> 3 | G9: =COUNTIFS('Test Cases'!$B:$B,"Orders",'Test Cases'!$L:$L,"Pass") -> 0 | H9: =COUNTIFS('Test Cases'!$B:$B,"Orders",'Test Cases'!$L:$L,"Fail") -> 0 | I9: =COUNTIFS('Test Cases'!$B:$B,"Orders",'Test Cases'!$L:$L,"Blocked") -> 0 | J9: =COUNTIFS('Test Cases'!$B:$B,"Orders",'Test Cases'!$L:$L,"Not Run") -> 0
B10: Trials | C10: =COUNTIF('Test Cases'!$B:$B,"Trials") -> 4 | D10: =COUNTIFS('Test Cases'!$B:$B,"Trials",'Test Cases'!$F:$F,"P1") -> 1 | E10: =COUNTIFS('Test Cases'!$B:$B,"Trials",'Test Cases'!$F:$F,"P2") -> 2 | F10: =COUNTIFS('Test Cases'!$B:$B,"Trials",'Test Cases'!$F:$F,"P3") -> 1 | G10: =COUNTIFS('Test Cases'!$B:$B,"Trials",'Test Cases'!$L:$L,"Pass") -> 0 | H10: =COUNTIFS('Test Cases'!$B:$B,"Trials",'Test Cases'!$L:$L,"Fail") -> 0 | I10: =COUNTIFS('Test Cases'!$B:$B,"Trials",'Test Cases'!$L:$L,"Blocked") -> 0 | J10: =COUNTIFS('Test Cases'!$B:$B,"Trials",'Test Cases'!$L:$L,"Not Run") -> 0
B11: Credit | C11: =COUNTIF('Test Cases'!$B:$B,"Credit") -> 2 | D11: =COUNTIFS('Test Cases'!$B:$B,"Credit",'Test Cases'!$F:$F,"P1") -> 0 | E11: =COUNTIFS('Test Cases'!$B:$B,"Credit",'Test Cases'!$F:$F,"P2") -> 1 | F11: =COUNTIFS('Test Cases'!$B:$B,"Credit",'Test Cases'!$F:$F,"P3") -> 1 | G11: =COUNTIFS('Test Cases'!$B:$B,"Credit",'Test Cases'!$L:$L,"Pass") -> 0 | H11: =COUNTIFS('Test Cases'!$B:$B,"Credit",'Test Cases'!$L:$L,"Fail") -> 0 | I11: =COUNTIFS('Test Cases'!$B:$B,"Credit",'Test Cases'!$L:$L,"Blocked") -> 0 | J11: =COUNTIFS('Test Cases'!$B:$B,"Credit",'Test Cases'!$L:$L,"Not Run") -> 0
B12: Invoices | C12: =COUNTIF('Test Cases'!$B:$B,"Invoices") -> 3 | D12: =COUNTIFS('Test Cases'!$B:$B,"Invoices",'Test Cases'!$F:$F,"P1") -> 0 | E12: =COUNTIFS('Test Cases'!$B:$B,"Invoices",'Test Cases'!$F:$F,"P2") -> 2 | F12: =COUNTIFS('Test Cases'!$B:$B,"Invoices",'Test Cases'!$F:$F,"P3") -> 1 | G12: =COUNTIFS('Test Cases'!$B:$B,"Invoices",'Test Cases'!$L:$L,"Pass") -> 0 | H12: =COUNTIFS('Test Cases'!$B:$B,"Invoices",'Test Cases'!$L:$L,"Fail") -> 0 | I12: =COUNTIFS('Test Cases'!$B:$B,"Invoices",'Test Cases'!$L:$L,"Blocked") -> 0 | J12: =COUNTIFS('Test Cases'!$B:$B,"Invoices",'Test Cases'!$L:$L,"Not Run") -> 0
B13: Coupons | C13: =COUNTIF('Test Cases'!$B:$B,"Coupons") -> 3 | D13: =COUNTIFS('Test Cases'!$B:$B,"Coupons",'Test Cases'!$F:$F,"P1") -> 0 | E13: =COUNTIFS('Test Cases'!$B:$B,"Coupons",'Test Cases'!$F:$F,"P2") -> 2 | F13: =COUNTIFS('Test Cases'!$B:$B,"Coupons",'Test Cases'!$F:$F,"P3") -> 1 | G13: =COUNTIFS('Test Cases'!$B:$B,"Coupons",'Test Cases'!$L:$L,"Pass") -> 0 | H13: =COUNTIFS('Test Cases'!$B:$B,"Coupons",'Test Cases'!$L:$L,"Fail") -> 0 | I13: =COUNTIFS('Test Cases'!$B:$B,"Coupons",'Test Cases'!$L:$L,"Blocked") -> 0 | J13: =COUNTIFS('Test Cases'!$B:$B,"Coupons",'Test Cases'!$L:$L,"Not Run") -> 0
B14: Leads | C14: =COUNTIF('Test Cases'!$B:$B,"Leads") -> 2 | D14: =COUNTIFS('Test Cases'!$B:$B,"Leads",'Test Cases'!$F:$F,"P1") -> 0 | E14: =COUNTIFS('Test Cases'!$B:$B,"Leads",'Test Cases'!$F:$F,"P2") -> 1 | F14: =COUNTIFS('Test Cases'!$B:$B,"Leads",'Test Cases'!$F:$F,"P3") -> 1 | G14: =COUNTIFS('Test Cases'!$B:$B,"Leads",'Test Cases'!$L:$L,"Pass") -> 0 | H14: =COUNTIFS('Test Cases'!$B:$B,"Leads",'Test Cases'!$L:$L,"Fail") -> 0 | I14: =COUNTIFS('Test Cases'!$B:$B,"Leads",'Test Cases'!$L:$L,"Blocked") -> 0 | J14: =COUNTIFS('Test Cases'!$B:$B,"Leads",'Test Cases'!$L:$L,"Not Run") -> 0
B15: Support | C15: =COUNTIF('Test Cases'!$B:$B,"Support") -> 6 | D15: =COUNTIFS('Test Cases'!$B:$B,"Support",'Test Cases'!$F:$F,"P1") -> 0 | E15: =COUNTIFS('Test Cases'!$B:$B,"Support",'Test Cases'!$F:$F,"P2") -> 3 | F15: =COUNTIFS('Test Cases'!$B:$B,"Support",'Test Cases'!$F:$F,"P3") -> 3 | G15: =COUNTIFS('Test Cases'!$B:$B,"Support",'Test Cases'!$L:$L,"Pass") -> 0 | H15: =COUNTIFS('Test Cases'!$B:$B,"Support",'Test Cases'!$L:$L,"Fail") -> 0 | I15: =COUNTIFS('Test Cases'!$B:$B,"Support",'Test Cases'!$L:$L,"Blocked") -> 0 | J15: =COUNTIFS('Test Cases'!$B:$B,"Support",'Test Cases'!$L:$L,"Not Run") -> 0
B16: Downloads | C16: =COUNTIF('Test Cases'!$B:$B,"Downloads") -> 6 | D16: =COUNTIFS('Test Cases'!$B:$B,"Downloads",'Test Cases'!$F:$F,"P1") -> 0 | E16: =COUNTIFS('Test Cases'!$B:$B,"Downloads",'Test Cases'!$F:$F,"P2") -> 3 | F16: =COUNTIFS('Test Cases'!$B:$B,"Downloads",'Test Cases'!$F:$F,"P3") -> 3 | G16: =COUNTIFS('Test Cases'!$B:$B,"Downloads",'Test Cases'!$L:$L,"Pass") -> 0 | H16: =COUNTIFS('Test Cases'!$B:$B,"Downloads",'Test Cases'!$L:$L,"Fail") -> 0 | I16: =COUNTIFS('Test Cases'!$B:$B,"Downloads",'Test Cases'!$L:$L,"Blocked") -> 0 | J16: =COUNTIFS('Test Cases'!$B:$B,"Downloads",'Test Cases'!$L:$L,"Not Run") -> 0
B17: Storage | C17: =COUNTIF('Test Cases'!$B:$B,"Storage") -> 2 | D17: =COUNTIFS('Test Cases'!$B:$B,"Storage",'Test Cases'!$F:$F,"P1") -> 0 | E17: =COUNTIFS('Test Cases'!$B:$B,"Storage",'Test Cases'!$F:$F,"P2") -> 0 | F17: =COUNTIFS('Test Cases'!$B:$B,"Storage",'Test Cases'!$F:$F,"P3") -> 2 | G17: =COUNTIFS('Test Cases'!$B:$B,"Storage",'Test Cases'!$L:$L,"Pass") -> 0 | H17: =COUNTIFS('Test Cases'!$B:$B,"Storage",'Test Cases'!$L:$L,"Fail") -> 0 | I17: =COUNTIFS('Test Cases'!$B:$B,"Storage",'Test Cases'!$L:$L,"Blocked") -> 0 | J17: =COUNTIFS('Test Cases'!$B:$B,"Storage",'Test Cases'!$L:$L,"Not Run") -> 0
B18: Plans | C18: =COUNTIF('Test Cases'!$B:$B,"Plans") -> 2 | D18: =COUNTIFS('Test Cases'!$B:$B,"Plans",'Test Cases'!$F:$F,"P1") -> 0 | E18: =COUNTIFS('Test Cases'!$B:$B,"Plans",'Test Cases'!$F:$F,"P2") -> 1 | F18: =COUNTIFS('Test Cases'!$B:$B,"Plans",'Test Cases'!$F:$F,"P3") -> 1 | G18: =COUNTIFS('Test Cases'!$B:$B,"Plans",'Test Cases'!$L:$L,"Pass") -> 0 | H18: =COUNTIFS('Test Cases'!$B:$B,"Plans",'Test Cases'!$L:$L,"Fail") -> 0 | I18: =COUNTIFS('Test Cases'!$B:$B,"Plans",'Test Cases'!$L:$L,"Blocked") -> 0 | J18: =COUNTIFS('Test Cases'!$B:$B,"Plans",'Test Cases'!$L:$L,"Not Run") -> 0
B19: Settings | C19: =COUNTIF('Test Cases'!$B:$B,"Settings") -> 5 | D19: =COUNTIFS('Test Cases'!$B:$B,"Settings",'Test Cases'!$F:$F,"P1") -> 1 | E19: =COUNTIFS('Test Cases'!$B:$B,"Settings",'Test Cases'!$F:$F,"P2") -> 3 | F19: =COUNTIFS('Test Cases'!$B:$B,"Settings",'Test Cases'!$F:$F,"P3") -> 1 | G19: =COUNTIFS('Test Cases'!$B:$B,"Settings",'Test Cases'!$L:$L,"Pass") -> 0 | H19: =COUNTIFS('Test Cases'!$B:$B,"Settings",'Test Cases'!$L:$L,"Fail") -> 0 | I19: =COUNTIFS('Test Cases'!$B:$B,"Settings",'Test Cases'!$L:$L,"Blocked") -> 0 | J19: =COUNTIFS('Test Cases'!$B:$B,"Settings",'Test Cases'!$L:$L,"Not Run") -> 0
B20: WA Templates | C20: =COUNTIF('Test Cases'!$B:$B,"WA Templates") -> 2 | D20: =COUNTIFS('Test Cases'!$B:$B,"WA Templates",'Test Cases'!$F:$F,"P1") -> 0 | E20: =COUNTIFS('Test Cases'!$B:$B,"WA Templates",'Test Cases'!$F:$F,"P2") -> 0 | F20: =COUNTIFS('Test Cases'!$B:$B,"WA Templates",'Test Cases'!$F:$F,"P3") -> 2 | G20: =COUNTIFS('Test Cases'!$B:$B,"WA Templates",'Test Cases'!$L:$L,"Pass") -> 0 | H20: =COUNTIFS('Test Cases'!$B:$B,"WA Templates",'Test Cases'!$L:$L,"Fail") -> 0 | I20: =COUNTIFS('Test Cases'!$B:$B,"WA Templates",'Test Cases'!$L:$L,"Blocked") -> 0 | J20: =COUNTIFS('Test Cases'!$B:$B,"WA Templates",'Test Cases'!$L:$L,"Not Run") -> 0
B21: Admin/RBAC | C21: =COUNTIF('Test Cases'!$B:$B,"Admin/RBAC") -> 6 | D21: =COUNTIFS('Test Cases'!$B:$B,"Admin/RBAC",'Test Cases'!$F:$F,"P1") -> 2 | E21: =COUNTIFS('Test Cases'!$B:$B,"Admin/RBAC",'Test Cases'!$F:$F,"P2") -> 2 | F21: =COUNTIFS('Test Cases'!$B:$B,"Admin/RBAC",'Test Cases'!$F:$F,"P3") -> 2 | G21: =COUNTIFS('Test Cases'!$B:$B,"Admin/RBAC",'Test Cases'!$L:$L,"Pass") -> 0 | H21: =COUNTIFS('Test Cases'!$B:$B,"Admin/RBAC",'Test Cases'!$L:$L,"Fail") -> 0 | I21: =COUNTIFS('Test Cases'!$B:$B,"Admin/RBAC",'Test Cases'!$L:$L,"Blocked") -> 0 | J21: =COUNTIFS('Test Cases'!$B:$B,"Admin/RBAC",'Test Cases'!$L:$L,"Not Run") -> 0
B22: Diagnostics | C22: =COUNTIF('Test Cases'!$B:$B,"Diagnostics") -> 2 | D22: =COUNTIFS('Test Cases'!$B:$B,"Diagnostics",'Test Cases'!$F:$F,"P1") -> 0 | E22: =COUNTIFS('Test Cases'!$B:$B,"Diagnostics",'Test Cases'!$F:$F,"P2") -> 1 | F22: =COUNTIFS('Test Cases'!$B:$B,"Diagnostics",'Test Cases'!$F:$F,"P3") -> 1 | G22: =COUNTIFS('Test Cases'!$B:$B,"Diagnostics",'Test Cases'!$L:$L,"Pass") -> 0 | H22: =COUNTIFS('Test Cases'!$B:$B,"Diagnostics",'Test Cases'!$L:$L,"Fail") -> 0 | I22: =COUNTIFS('Test Cases'!$B:$B,"Diagnostics",'Test Cases'!$L:$L,"Blocked") -> 0 | J22: =COUNTIFS('Test Cases'!$B:$B,"Diagnostics",'Test Cases'!$L:$L,"Not Run") -> 0
B23: Audit | C23: =COUNTIF('Test Cases'!$B:$B,"Audit") -> 2 | D23: =COUNTIFS('Test Cases'!$B:$B,"Audit",'Test Cases'!$F:$F,"P1") -> 0 | E23: =COUNTIFS('Test Cases'!$B:$B,"Audit",'Test Cases'!$F:$F,"P2") -> 1 | F23: =COUNTIFS('Test Cases'!$B:$B,"Audit",'Test Cases'!$F:$F,"P3") -> 1 | G23: =COUNTIFS('Test Cases'!$B:$B,"Audit",'Test Cases'!$L:$L,"Pass") -> 0 | H23: =COUNTIFS('Test Cases'!$B:$B,"Audit",'Test Cases'!$L:$L,"Fail") -> 0 | I23: =COUNTIFS('Test Cases'!$B:$B,"Audit",'Test Cases'!$L:$L,"Blocked") -> 0 | J23: =COUNTIFS('Test Cases'!$B:$B,"Audit",'Test Cases'!$L:$L,"Not Run") -> 0
B24: Reports | C24: =COUNTIF('Test Cases'!$B:$B,"Reports") -> 4 | D24: =COUNTIFS('Test Cases'!$B:$B,"Reports",'Test Cases'!$F:$F,"P1") -> 0 | E24: =COUNTIFS('Test Cases'!$B:$B,"Reports",'Test Cases'!$F:$F,"P2") -> 2 | F24: =COUNTIFS('Test Cases'!$B:$B,"Reports",'Test Cases'!$F:$F,"P3") -> 2 | G24: =COUNTIFS('Test Cases'!$B:$B,"Reports",'Test Cases'!$L:$L,"Pass") -> 0 | H24: =COUNTIFS('Test Cases'!$B:$B,"Reports",'Test Cases'!$L:$L,"Fail") -> 0 | I24: =COUNTIFS('Test Cases'!$B:$B,"Reports",'Test Cases'!$L:$L,"Blocked") -> 0 | J24: =COUNTIFS('Test Cases'!$B:$B,"Reports",'Test Cases'!$L:$L,"Not Run") -> 0
B25: Checkout | C25: =COUNTIF('Test Cases'!$B:$B,"Checkout") -> 2 | D25: =COUNTIFS('Test Cases'!$B:$B,"Checkout",'Test Cases'!$F:$F,"P1") -> 0 | E25: =COUNTIFS('Test Cases'!$B:$B,"Checkout",'Test Cases'!$F:$F,"P2") -> 2 | F25: =COUNTIFS('Test Cases'!$B:$B,"Checkout",'Test Cases'!$F:$F,"P3") -> 0 | G25: =COUNTIFS('Test Cases'!$B:$B,"Checkout",'Test Cases'!$L:$L,"Pass") -> 0 | H25: =COUNTIFS('Test Cases'!$B:$B,"Checkout",'Test Cases'!$L:$L,"Fail") -> 0 | I25: =COUNTIFS('Test Cases'!$B:$B,"Checkout",'Test Cases'!$L:$L,"Blocked") -> 0 | J25: =COUNTIFS('Test Cases'!$B:$B,"Checkout",'Test Cases'!$L:$L,"Not Run") -> 0
B26: Webhooks | C26: =COUNTIF('Test Cases'!$B:$B,"Webhooks") -> 2 | D26: =COUNTIFS('Test Cases'!$B:$B,"Webhooks",'Test Cases'!$F:$F,"P1") -> 0 | E26: =COUNTIFS('Test Cases'!$B:$B,"Webhooks",'Test Cases'!$F:$F,"P2") -> 1 | F26: =COUNTIFS('Test Cases'!$B:$B,"Webhooks",'Test Cases'!$F:$F,"P3") -> 1 | G26: =COUNTIFS('Test Cases'!$B:$B,"Webhooks",'Test Cases'!$L:$L,"Pass") -> 0 | H26: =COUNTIFS('Test Cases'!$B:$B,"Webhooks",'Test Cases'!$L:$L,"Fail") -> 0 | I26: =COUNTIFS('Test Cases'!$B:$B,"Webhooks",'Test Cases'!$L:$L,"Blocked") -> 0 | J26: =COUNTIFS('Test Cases'!$B:$B,"Webhooks",'Test Cases'!$L:$L,"Not Run") -> 0
B27: Cross | C27: =COUNTIF('Test Cases'!$B:$B,"Cross") -> 5 | D27: =COUNTIFS('Test Cases'!$B:$B,"Cross",'Test Cases'!$F:$F,"P1") -> 0 | E27: =COUNTIFS('Test Cases'!$B:$B,"Cross",'Test Cases'!$F:$F,"P2") -> 2 | F27: =COUNTIFS('Test Cases'!$B:$B,"Cross",'Test Cases'!$F:$F,"P3") -> 3 | G27: =COUNTIFS('Test Cases'!$B:$B,"Cross",'Test Cases'!$L:$L,"Pass") -> 0 | H27: =COUNTIFS('Test Cases'!$B:$B,"Cross",'Test Cases'!$L:$L,"Fail") -> 0 | I27: =COUNTIFS('Test Cases'!$B:$B,"Cross",'Test Cases'!$L:$L,"Blocked") -> 0 | J27: =COUNTIFS('Test Cases'!$B:$B,"Cross",'Test Cases'!$L:$L,"Not Run") -> 0
B28: TOTAL (module sheet) | C28: =SUM(C5:C27) -> 103 | D28: =SUM(D5:D27) -> 13 | E28: =SUM(E5:E27) -> 52 | F28: =SUM(F5:F27) -> 38 | G28: =SUM(G5:G27) -> 0 | H28: =SUM(H5:H27) -> 0 | I28: =SUM(I5:I27) -> 0 | J28: =SUM(J5:J27) -> 0
B30: Note: the 10 QA round-2 cases are on the 'Bug-Fix Verification (R2)' sheet; the counts above cover the module 'Test Cases' sheet.
